nirfmxbluetooth/__init__.py
nirfmxbluetooth/acp.py
nirfmxbluetooth/acp_configuration.py
nirfmxbluetooth/acp_results.py
nirfmxbluetooth/attributes.py
nirfmxbluetooth/bluetooth.py
nirfmxbluetooth/enums.py
nirfmxbluetooth/errors.py
nirfmxbluetooth/examples/nirfmxbluetooth_acp.py
nirfmxbluetooth/examples/nirfmxbluetooth_devm_grpc.py
nirfmxbluetooth/examples/nirfmxbluetooth_hdt_modacc.py
nirfmxbluetooth/examples/nirfmxbluetooth_txp.py
nirfmxbluetooth/frequency_range.py
nirfmxbluetooth/frequency_range_configuration.py
nirfmxbluetooth/frequency_range_results.py
nirfmxbluetooth/grpc_session_options.py
nirfmxbluetooth/internal/_custom_types.py
nirfmxbluetooth/internal/_grpc_stub_interpreter.py
nirfmxbluetooth/internal/_helper.py
nirfmxbluetooth/internal/_library.py
nirfmxbluetooth/internal/_library_interpreter.py
nirfmxbluetooth/internal/_library_singleton.py
nirfmxbluetooth/internal/nidevice_pb2.py
nirfmxbluetooth/internal/nidevice_pb2_grpc.py
nirfmxbluetooth/internal/nirfmxbluetooth_pb2.py
nirfmxbluetooth/internal/nirfmxbluetooth_pb2_grpc.py
nirfmxbluetooth/internal/session_pb2.py
nirfmxbluetooth/internal/session_pb2_grpc.py
nirfmxbluetooth/modacc.py
nirfmxbluetooth/modacc_configuration.py
nirfmxbluetooth/modacc_results.py
nirfmxbluetooth/modspectrum.py
nirfmxbluetooth/modspectrum_configuration.py
nirfmxbluetooth/modspectrum_results.py
nirfmxbluetooth/powerramp.py
nirfmxbluetooth/powerramp_configuration.py
nirfmxbluetooth/powerramp_results.py
nirfmxbluetooth/twenty_db_bandwidth.py
nirfmxbluetooth/twenty_db_bandwidth_configuration.py
nirfmxbluetooth/twenty_db_bandwidth_results.py
nirfmxbluetooth/txp.py
nirfmxbluetooth/txp_configuration.py
nirfmxbluetooth/txp_results.py
nirfmxbluetooth-26.0.0.dist-info/licenses/LICENSE
nirfmxbluetooth-26.0.0.dist-info/METADATA
nirfmxbluetooth-26.0.0.dist-info/WHEEL
nirfmxbluetooth-26.0.0.dist-info/RECORD
